Metadata-Version: 1.0
Name: chin-dsnd
Version: 0.1
Summary: Gaussian distributions and Binomial distributions
Home-page: UNKNOWN
Author: Chinmay kumar Das
Author-email: chinmaydasbat@gmail.com
License: UNKNOWN
Platform: UNKNOWN
